LICENSE.txt
MANIFEST.in
README.rst
setup.py
agent_client/__init__.py
agent_client/api.py
agent_client/db_client.py
agent_client/rest_client.py
agent_client.egg-info/PKG-INFO
agent_client.egg-info/SOURCES.txt
agent_client.egg-info/dependency_links.txt
agent_client.egg-info/requires.txt
agent_client.egg-info/top_level.txt
agent_client/configuration/database.yaml
agent_client/resources/__init__.py
agent_client/resources/dut_database.py
agent_client/resources/dut_rest_resource.py
agent_client/resources/models/__init__.py
agent_client/resources/models/database.py
agent_client/resources/models/ftp_client.py
agent_client/resources/models/helper.py
agent_client/resources/models/remoter.py