Metadata-Version: 1.1
Name: agent-client
Version: 1.1.4
Summary: REST Runner
Home-page: https://pypi.org/project/agent_client
Author: yuwen123441
Author-email: yuwen123441@126.com
License: MIT License
Keywords: runner,client
Platform: any
Classifier: Development Status :: 3 - Alpha
Classifier: Intended Audience :: Developers
Classifier: Topic :: Software Development :: Libraries
Classifier: License :: OSI Approved :: MIT License
Classifier: Programming Language :: Python :: 3.6
